quiktools/__init__.py
quiktools-0.1.dist-info/LICENSE
quiktools-0.1.dist-info/METADATA
quiktools-0.1.dist-info/WHEEL
quiktools-0.1.dist-info/top_level.txt
quiktools-0.1.dist-info/RECORD
