Metadata-Version: 2.1
Name: quiktools
Version: 0.1
Summary: Quickly do things in 1 line that would've taken multiple lines.
Author: noerlol
Author-email: noerlol@proton.com
License-File: LICENSE
